python_notion_plus/__init__.py
python_notion_plus/notion.py
python_notion_plus/usage_example.py
python_notion_plus-0.0.7.dist-info/licenses/LICENSE
python_notion_plus-0.0.7.dist-info/METADATA
python_notion_plus-0.0.7.dist-info/WHEEL
python_notion_plus-0.0.7.dist-info/top_level.txt
python_notion_plus-0.0.7.dist-info/RECORD
