Metadata-Version: 2.4
Name: python-notion-plus
Version: 0.0.7
Summary: Python wrapper for Notion API
Home-page: https://github.com/aviz92/python-notion-plus
Author: Avi Zaguri
Author-email: 
Project-URL: Repository, https://github.com/aviz92/python-notion-plus
Requires-Python: >=3.11
License-File: LICENSE
Requires-Dist: setuptools
Requires-Dist: wheel
Requires-Dist: python-dotenv
Requires-Dist: pre-commit
Requires-Dist: twine
Requires-Dist: pytest
Requires-Dist: retrying
Requires-Dist: notion_client
Requires-Dist: pytz
Requires-Dist: custom-python-logger
Dynamic: author
Dynamic: description
Dynamic: description-content-type
Dynamic: home-page
Dynamic: license-file
Dynamic: project-url
Dynamic: requires-dist
Dynamic: requires-python
Dynamic: summary
